odoo/addons/document_page_health_safety_manual/README.rst
odoo/addons/document_page_health_safety_manual/__init__.py
odoo/addons/document_page_health_safety_manual/__manifest__.py
odoo/addons/document_page_health_safety_manual/data/document_page.xml
odoo/addons/document_page_health_safety_manual/i18n/document_page_health_safety_manual.pot
odoo/addons/document_page_health_safety_manual/i18n/it.po
odoo/addons/document_page_health_safety_manual/readme/CONTRIBUTORS.rst
odoo/addons/document_page_health_safety_manual/readme/DESCRIPTION.rst
odoo/addons/document_page_health_safety_manual/readme/ROADMAP.rst
odoo/addons/document_page_health_safety_manual/readme/USAGE.rst
odoo/addons/document_page_health_safety_manual/static/description/icon.png
odoo/addons/document_page_health_safety_manual/static/description/index.html
odoo13_addon_document_page_health_safety_manual-13.0.1.0.1.dev6.dist-info/METADATA
odoo13_addon_document_page_health_safety_manual-13.0.1.0.1.dev6.dist-info/WHEEL
odoo13_addon_document_page_health_safety_manual-13.0.1.0.1.dev6.dist-info/top_level.txt
odoo13_addon_document_page_health_safety_manual-13.0.1.0.1.dev6.dist-info/RECORD
